
{
    "ingredients": [
        {
            "name": "beurre",
            "id": 1,
            "quantite": 100,
            "proteine": 0.7,
            "lipide": 82,
            "glucide": 0.5
        },
        {
            "name": "lait",
            "id": 2,
            "quantite": 1,
            "proteine": 0.33,
            "lipide": 0.16,
            "glucide": 0.48
        },
        {
            "name": "farine de  t45 gruau",
            "id": 3,
            "quantite": 100,
            "proteine": 10.1,
            "lipide": 1.1,
            "glucide": 75.9
        },
        {
            "name": "farine t45",
            "id": 4,
            "quantite": 100,
            "proteine": 8.5,
            "lipide": 1,
            "glucide": 71
        },
        {
            "name": "levure boulangere",
            "id": 5,
            "quantite": 100,
            "proteine": 8,
            "lipide": 1.9,
            "glucide": 18
        },
        {
            "name": "oeuf",
            "id": 6,
            "quantite": 1,
            "proteine": 6,
            "lipide": 5,
            "glucide": 1
        },
        {
            "name": "sucre",
            "id": 7,
            "quantite": 100,
            "proteine": 0,
            "lipide": 0,
            "glucide": 100
        },
        {
            "name": "sel",
            "id": 8,
            "quantite": 100,
            "proteine": 0,
            "lipide": 0,
            "glucide": 0
        },
        {
            "name": "huile d'olive",
            "id": 9,
            "quantite": 1,
            "proteine": 0,
            "lipide": 9.2,
            "glucide": 0
        },
        {
            "name": "cacao en poudre",
            "id": 10,
            "quantite": 100,
            "proteine": 20,
            "lipide": 21,
            "glucide": 11
        },
        {
            "name": "chocolat en tablette",
            "id": 11,
            "quantite": 100,
            "proteine": 7,
            "lipide": 30,
            "glucide": 51
        },
        {
            "name": "levure chimique",
            "id": 12,
            "quantite": 100,
            "proteine": 0,
            "lipide": 0,
            "glucide": 0
        },
        {
            "name": "crème liquide 30%",
            "id": 13,
            "quantite": 1,
            "proteine": 0.24,
            "lipide": 3,
            "glucide": 0.34
        },
        {
            "name": "crème liquide 15%",
            "id": 14,
            "quantite": 1,
            "proteine": 0.3,
            "lipide": 1.5,
            "glucide": 0.48
        },
        {
            "name": "crème liquide 12%",
            "id": 15,
            "quantite": 1,
            "proteine": 0.31,
            "lipide": 1.2,
            "glucide": 0.45
        },
        {
            "name": "sucre vanille",
            "id": 16,
            "quantite": 1,
            "proteine": 0.03,
            "lipide": 0.03,
            "glucide": 7.42
        },
        {
            "name": "feuille de gélatine",
            "id": 17,
            "quantite": 1,
            "proteine": 0,
            "lipide": 0,
            "glucide": 0
        },
        {
            "name": "eau",
            "id": 18,
            "quantite": 1,
            "proteine": 0,
            "lipide": 0,
            "glucide": 0
        },
        {
            "name": "jaune d'oeuf",
            "id": 19,
            "quantite": 1,
            "proteine": 3,
            "lipide": 5,
            "glucide": 0
        },
        {
            "name": "blanc d'oeuf",
            "id": 20,
            "quantite": 1,
            "proteine": 3,
            "lipide": 0,
            "glucide": 0
        },
        {
            "name": "maizena",
            "id": 21,
            "quantite": 100,
            "proteine": 0.5,
            "lipide": 0.5,
            "glucide": 86
        },
        {
            "name": "jus de citron",
            "id": 22,
            "quantite": 100,
            "proteine": 0,
            "lipide": 0,
            "glucide": 0
        },
        {
            "name": "citron",
            "id": 23,
            "quantite": 100,
            "proteine": 0,
            "lipide": 0,
            "glucide": 0
        }
    ]
}